iqa/__init__.py
iqa/psnr.py
iqa/ssim.py
iqa/version.py
iqa/lpips/__init__.py
iqa/lpips/lpips.py
iqa/lpips/lpips_model.py
iqa/lpips/pretrained_networks.py
iqa/lpips/weights/v0.0/alex.pth
iqa/lpips/weights/v0.0/squeeze.pth
iqa/lpips/weights/v0.0/vgg.pth
iqa/lpips/weights/v0.1/alex.pth
iqa/lpips/weights/v0.1/squeeze.pth
iqa/lpips/weights/v0.1/vgg.pth
iqa/niqe/__init__.py
iqa/niqe/niqe.py
iqa/niqe/niqe_core.py
iqa/niqe/niqe_pris_params.npz
iqa/niqe/utils.py
iqa/utils/__init__.py
iqa/utils/csc.py
iqa/utils/image_utils.py
iqa_torch-1.2.1.dist-info/LICENSE
iqa_torch-1.2.1.dist-info/METADATA
iqa_torch-1.2.1.dist-info/WHEEL
iqa_torch-1.2.1.dist-info/top_level.txt
iqa_torch-1.2.1.dist-info/RECORD
